indegreeparser/__init__.py
indegreeparser/command_line.py
indegreeparser/constants.py
indegreeparser/custom_t.py
indegreeparser/custom_train.py
indegreeparser/resume_parser.py
indegreeparser/utils.py
indegreeparser-1.0.1.dist-info/LICENSE
indegreeparser-1.0.1.dist-info/METADATA
indegreeparser-1.0.1.dist-info/WHEEL
indegreeparser-1.0.1.dist-info/entry_points.txt
indegreeparser-1.0.1.dist-info/top_level.txt
indegreeparser-1.0.1.dist-info/RECORD
